thoughtforge_client/__init__.py
thoughtforge_client/thoughtforge_client.py
thoughtforge_client/utils/__init__.py
thoughtforge_client/utils/behavior_interface.py
thoughtforge_client/utils/client_param_utils.py
thoughtforge_client/utils/sensor_motor_groups.py
thoughtforge_client/utils/signals_and_derivatives.py
thoughtforge_client/utils/value_delta.py
thoughtforge_client-1.0.2.dist-info/LICENSE.md
thoughtforge_client-1.0.2.dist-info/METADATA
thoughtforge_client-1.0.2.dist-info/WHEEL
thoughtforge_client-1.0.2.dist-info/top_level.txt
thoughtforge_client-1.0.2.dist-info/RECORD
