Metadata-Version: 2.1
Name: thoughtforge_client
Version: 1.0.2
Summary: Client SDK Package for ThoughtForge AI
Home-page: https://github.com/thoughtforge-ai/thoughtforge-client
Author: Matthew Brown
Author-email: matt@thoughtforge.ai
License: UNKNOWN
Platform: UNKNOWN
Classifier: Programming Language :: Python :: 3
Classifier: License :: OSI Approved :: MIT License
Classifier: Operating System :: OS Independent
Requires-Python: >=3.6
License-File: LICENSE.md
